sdds/SDDS1.dll
sdds/__init__.py
sdds/lzma.dll
sdds/matlib.dll
sdds/mdbcommon.dll
sdds/mdblib.dll
sdds/mdbmth.dll
sdds/rpnlib.dll
sdds/sdds.py
sdds/sddsdata.pyd
soliday.sdds-5.7.2.dist-info/LICENSE
soliday.sdds-5.7.2.dist-info/METADATA
soliday.sdds-5.7.2.dist-info/WHEEL
soliday.sdds-5.7.2.dist-info/top_level.txt
soliday.sdds-5.7.2.dist-info/RECORD
