Metadata-Version: 2.1
Name: soliday.sdds
Version: 5.7.2
Summary: Official Python interface for the SDDS (Self Describing Data Sets) format.
Home-page: https://www.aps.anl.gov/Accelerator-Operations-Physics/Software
Author: Robert Soliday
Author-email: Robert Soliday <soliday@anl.gov>
License: SDDS Toolkit License
Project-URL: Homepage, https://www.aps.anl.gov/Accelerator-Operations-Physics/Software
Platform: windows-x64
Classifier: Programming Language :: Python :: 3
Classifier: License :: Other/Proprietary License
Classifier: Operating System :: POSIX :: Linux
Classifier: Operating System :: Unix
Classifier: Operating System :: POSIX
Classifier: Operating System :: MacOS :: MacOS X
Classifier: Operating System :: Microsoft :: Windows
Requires-Python: >=3.9,<3.10
License-File: LICENSE
